revli/__init__.py
revli/__main__.py
revli/cli.py
revli/data/mapbox-gl.js
revli/data/reveald3.js
revli/data/tagcloud.js
revli/data/chalkboard/README.md
revli/data/chalkboard/chalkboard.js
revli/data/chalkboard/img/blackboard.png
revli/data/chalkboard/img/boardmarker-black.png
revli/data/chalkboard/img/boardmarker-blue.png
revli/data/chalkboard/img/boardmarker-green.png
revli/data/chalkboard/img/boardmarker-orange.png
revli/data/chalkboard/img/boardmarker-purple.png
revli/data/chalkboard/img/boardmarker-red.png
revli/data/chalkboard/img/boardmarker-yellow.png
revli/data/chalkboard/img/chalk-blue.png
revli/data/chalkboard/img/chalk-green.png
revli/data/chalkboard/img/chalk-orange.png
revli/data/chalkboard/img/chalk-purple.png
revli/data/chalkboard/img/chalk-red.png
revli/data/chalkboard/img/chalk-white.png
revli/data/chalkboard/img/chalk-yellow.png
revli/data/chalkboard/img/sponge.png
revli/data/chalkboard/img/whiteboard.png
revli/data/chart/Chart.js
revli/data/chart/Chart.min.js
revli/data/chart/README.md
revli/data/chart/chart_plugin.js
revli/data/multiplex/.gitignore
revli/data/multiplex/LICENSE
revli/data/multiplex/README.md
revli/data/multiplex/client.js
revli/data/multiplex/index.js
revli/data/multiplex/master.js
revli/data/multiplex/package-lock.json
revli/data/multiplex/package.json
revli/data/multiplex/socket.io.js
revli/data/otf-fragment-order/README.md
revli/data/otf-fragment-order/otf-fragment-order.coffee
revli/data/otf-fragment-order/otf-fragment-order.js
revli/data/otf-fragment-order/otf-fragment-order.js.map
revli/data/reveal.js/.gitignore
revli/data/reveal.js/.npmignore
revli/data/reveal.js/CONTRIBUTING.md
revli/data/reveal.js/LICENSE
revli/data/reveal.js/README.md
revli/data/reveal.js/demo.html
revli/data/reveal.js/gulpfile.js
revli/data/reveal.js/index.html
revli/data/reveal.js/package-lock.json
revli/data/reveal.js/package.json
revli/data/reveal.js/.github/FUNDING.yml
revli/data/reveal.js/.github/workflows/js.yml
revli-0.1.0.dist-info/LICENSE
revli-0.1.0.dist-info/METADATA
revli-0.1.0.dist-info/WHEEL
revli-0.1.0.dist-info/entry_points.txt
revli-0.1.0.dist-info/top_level.txt
revli-0.1.0.dist-info/RECORD
