Metadata-Version: 2.1
Name: revli
Version: 0.1.0
Summary: revli is a cli tool to create reveal.js presentations and manage their plugins
Home-page: https://github.com/Akida31/revli
Author: Akida31
License: UNKNOWN
Platform: UNKNOWN
Classifier: Programming Language :: Python :: 3
Classifier: License :: OSI Approved :: MIT License
Classifier: Operating System :: OS Independent
Classifier: Topic :: Multimedia :: Graphics :: Presentation
Requires-Python: >=3.8
Requires-Dist: beautifulsoup4
Requires-Dist: chompjs
